reader/__init__.py
reader/__main__.py
reader/config.cfg
reader/feed.py
reader/viewer.py
sipian_test_package_1-1.0.0.dist-info/LICENSE
sipian_test_package_1-1.0.0.dist-info/METADATA
sipian_test_package_1-1.0.0.dist-info/WHEEL
sipian_test_package_1-1.0.0.dist-info/entry_points.txt
sipian_test_package_1-1.0.0.dist-info/top_level.txt
sipian_test_package_1-1.0.0.dist-info/RECORD
