Metadata-Version: 2.1
Name: sipian-test-package-1
Version: 1.0.0
Summary: Read the latest Real Python tutorials
Home-page: https://github.com/sipian/reader
Author: Harsh Agarwal
Author-email: harshaga97@gmail.com
License: MIT
Platform: UNKNOWN
Classifier: License :: OSI Approved :: MIT License
Classifier: Programming Language :: Python
Classifier: Programming Language :: Python :: 2
Classifier: Programming Language :: Python :: 3
Requires-Dist: feedparser
Requires-Dist: html2text
Requires-Dist: importlib-resources
Requires-Dist: typing
